ai_policy/__init__.py
ai_policy-0.0.2.dist-info/METADATA
ai_policy-0.0.2.dist-info/WHEEL
ai_policy-0.0.2.dist-info/RECORD
